	{
		"uniqueId":898,
		"id":"20tdnc",
		"songFileName":"song_20tdnc",
		"order":1619,
		"genreNo":7,
		"branchEasy":false,
		"branchNormal":false,
		"branchHard":false,
		"branchMania":false,
		"branchUra":false,
		"starEasy":4,
		"starNormal":6,
		"starHard":6,
		"starMania":8,
		"starUra":0,
		"shinutiEasy":6880,
		"shinutiNormal":4460,
		"shinutiHard":3160,
		"shinutiMania":1670,
		"shinutiUra":0,
		"shinutiEasyDuet":6880,
		"shinutiNormalDuet":4460,
		"shinutiHardDuet":3160,
		"shinutiManiaDuet":1670,
		"shinutiUraDuet":0,
		"scoreEasy":1000800,
		"scoreNormal":1001040,
		"scoreHard":1000360,
		"scoreMania":1001010,
		"scoreUra":0,
		"previewPos":55203,
		"fumenOffsetPos":0,
		"songName": {
			"text": "Ｈｏｌｄ ｍｅ ｔｉｇｈｔ",
			"font": 0,
			"jpText": "Ｈｏｌｄ ｍｅ ｔｉｇｈｔ",
			"jpFont": 0,
			"enText": "Hold me tight",
			"enFont": 1,
			"krText": "Hold me tight",
			"krFont": 4
		},
		"songSubtitle": {
			"text": "太鼓 de タイムトラベル90's / Tatsh&musica with パークマンサー",
			"font": 0,
			"jpText": "太鼓 de タイムトラベル90's / Tatsh&musica with パークマンサー",
			"jpFont": 0,
			"enText": "Taiko de Time Travel 90's / Tatsh&musica with Parc Manther",
			"enFont": 1,
			"krText": "태고로 시간여행 90's / Tatsh&musica with 파크맨서",
			"krFont": 4
		},
		"songDetail": {
			"text": "",
			"font": 0,
			"jpText": "",
			"jpFont": 0,
			"enText": "",
			"enFont": 0,
			"krText": "",
			"krFont": 0
		}
	}