	{
		"uniqueId":191,
		"id":"dptfct",
		"songFileName":"song_dptfct",
		"order":1483,
		"genreNo":7,
		"branchEasy":false,
		"branchNormal":false,
		"branchHard":false,
		"branchMania":false,
		"branchUra":false,
		"starEasy":5,
		"starNormal":6,
		"starHard":8,
		"starMania":10,
		"starUra":0,
		"shinutiEasy":4560,
		"shinutiNormal":3180,
		"shinutiHard":1960,
		"shinutiMania":1290,
		"shinutiUra":0,
		"shinutiEasyDuet":4560,
		"shinutiNormalDuet":3180,
		"shinutiHardDuet":1960,
		"shinutiManiaDuet":1290,
		"shinutiUraDuet":0,
		"scoreEasy":1001540,
		"scoreNormal":1000840,
		"scoreHard":1000180,
		"scoreMania":1003230,
		"scoreUra":0,
		"previewPos":51100,
		"fumenOffsetPos":20,
		"songName": {
			"text": "wonderful ROUTINE",
			"font": 0,
			"jpText": "wonderful ROUTINE",
			"jpFont": 0,
			"enText": "wonderful ROUTINE",
			"enFont": 1,
			"krText": "wonderful ROUTINE",
			"krFont": 4
		},
		"songSubtitle": {
			"text": "",
			"font": 0,
			"jpText": "",
			"jpFont": 0,
			"enText": "",
			"enFont": 1,
			"krText": "",
			"krFont": 4
		},
		"songDetail": {
			"text": "",
			"font": 0,
			"jpText": "",
			"jpFont": 0,
			"enText": "",
			"enFont": 0,
			"krText": "",
			"krFont": 0
		}
	}