	{
		"uniqueId":1901,
		"id":"bshar2",
		"songFileName":"song_bshar2",
		"order":1129,
		"genreNo":3,
		"branchEasy":false,
		"branchNormal":false,
		"branchHard":false,
		"branchMania":false,
		"branchUra":false,
		"starEasy":1,
		"starNormal":1,
		"starHard":3,
		"starMania":4,
		"starUra":0,
		"shinutiEasy":23260,
		"shinutiNormal":13160,
		"shinutiHard":6500,
		"shinutiMania":3850,
		"shinutiUra":0,
		"shinutiEasyDuet":23260,
		"shinutiNormalDuet":13160,
		"shinutiHardDuet":6500,
		"shinutiManiaDuet":3850,
		"shinutiUraDuet":0,
		"scoreEasy":1000180,
		"scoreNormal":1000160,
		"scoreHard":1001000,
		"scoreMania":1001000,
		"scoreUra":0,
		"previewPos":11655,
		"fumenOffsetPos":-8,
		"songName": {
			"text": "Baby Shark",
			"font": 0,
			"jpText": "Baby Shark",
			"jpFont": 0,
			"enText": "Baby Shark",
			"enFont": 1,
			"krText": "Baby Shark",
			"krFont": 4
		},
		"songSubtitle": {
			"text": "太鼓の達人 Pop Tap Beat feat. ののちゃん",
			"font": 0,
			"jpText": "太鼓の達人 Pop Tap Beat feat. ののちゃん",
			"jpFont": 0,
			"enText": "Taiko no Tatsujin Pop Tap Beat feat. Nonoka",
			"enFont": 1,
			"krText": "",
			"krFont": 4
		},
		"songDetail": {
			"text": "",
			"font": 0,
			"jpText": "",
			"jpFont": 0,
			"enText": "",
			"enFont": 0,
			"krText": "",
			"krFont": 0
		}
	}