	{
		"uniqueId":796,
		"id":"ybtwed",
		"songFileName":"song_ybtwed",
		"order":1558,
		"genreNo":0,
		"branchEasy":false,
		"branchNormal":false,
		"branchHard":false,
		"branchMania":false,
		"branchUra":false,
		"starEasy":1,
		"starNormal":2,
		"starHard":3,
		"starMania":6,
		"starUra":8,
		"shinutiEasy":18340,
		"shinutiNormal":11640,
		"shinutiHard":6100,
		"shinutiMania":3640,
		"shinutiUra":2410,
		"shinutiEasyDuet":18340,
		"shinutiNormalDuet":11640,
		"shinutiHardDuet":6100,
		"shinutiManiaDuet":3640,
		"shinutiUraDuet":2410,
		"scoreEasy":1000160,
		"scoreNormal":1000300,
		"scoreHard":1001400,
		"scoreMania":1000580,
		"scoreUra":2410,
		"previewPos":53655,
		"fumenOffsetPos":20,
		"songName": {
			"text": "ハッピーウェディング前ソング",
			"font": 0,
			"jpText": "ハッピーウェディング前ソング",
			"jpFont": 0,
			"enText": "Happy Wedding-mae Song",
			"enFont": 1,
			"krText": "해피 웨딩 전 송",
			"krFont": 4
		},
		"songSubtitle": {
			"text": "ヤバイTシャツ屋さん",
			"font": 0,
			"jpText": "ヤバイTシャツ屋さん",
			"jpFont": 0,
			"enText": "Yabai T-Shirts Yasan",
			"enFont": 1,
			"krText": "위험한 티셔츠가게",
			"krFont": 4
		},
		"songDetail": {
			"text": "",
			"font": 0,
			"jpText": "",
			"jpFont": 0,
			"enText": "ハッピーウェディング前ソング",
			"enFont": 0,
			"krText": "ハッピーウェディング前ソング",
			"krFont": 0
		}
	}