	{
		"uniqueId":712,
		"id":"thmrs",
		"songFileName":"song_thmrs",
		"order":1967,
		"genreNo":3,
		"branchEasy":false,
		"branchNormal":false,
		"branchHard":false,
		"branchMania":false,
		"branchUra":false,
		"starEasy":4,
		"starNormal":5,
		"starHard":6,
		"starMania":9,
		"starUra":0,
		"shinutiEasy":6550,
		"shinutiNormal":4630,
		"shinutiHard":2260,
		"shinutiMania":1230,
		"shinutiUra":0,
		"shinutiEasyDuet":6550,
		"shinutiNormalDuet":4630,
		"shinutiHardDuet":2260,
		"shinutiManiaDuet":1230,
		"shinutiUraDuet":0,
		"scoreEasy":1001450,
		"scoreNormal":1001620,
		"scoreHard":1003620,
		"scoreMania":1000200,
		"scoreUra":0,
		"previewPos":46774,
		"fumenOffsetPos":20,
		"songName": {
			"text": "魔理沙は大変なものを盗んでいきました",
			"font": 0,
			"jpText": "魔理沙は大変なものを盗んでいきました",
			"jpFont": 0,
			"enText": "Marisa Wa Taihen Na Mono Wo Nusunde Ikimashita",
			"enFont": 1,
			"krText": "마리사는 엄청난 것을 훔쳐갔습니다",
			"krFont": 4
		},
		"songSubtitle": {
			"text": "東方Projectアレンジ ARM+夕野ヨシミ(IOSYS) feat.藤咲かりん",
			"font": 0,
			"jpText": "東方Projectアレンジ ARM+夕野ヨシミ(IOSYS) feat.藤咲かりん",
			"jpFont": 0,
			"enText": "Touhou Project Arrange / ARM+Youno Yoshimi(IOSYS) feat. Fujisaki Karin",
			"enFont": 1,
			"krText": "동방 Project 어레인지 - ARM+유우노 요시미(IOSYS) feat.후지사키 카린",
			"krFont": 4
		},
		"songDetail": {
			"text": "",
			"font": 0,
			"jpText": "",
			"jpFont": 0,
			"enText": "魔理沙は大変なものを盗んでいきました",
			"enFont": 0,
			"krText": "魔理沙は大変なものを盗んでいきました",
			"krFont": 0
		}
	}