	{
		"uniqueId":570,
		"id":"rainmk",
		"songFileName":"song_rainmk",
		"order":2259,
		"genreNo":6,
		"branchEasy":false,
		"branchNormal":false,
		"branchHard":false,
		"branchMania":false,
		"branchUra":false,
		"starEasy":3,
		"starNormal":4,
		"starHard":5,
		"starMania":8,
		"starUra":0,
		"shinutiEasy":6310,
		"shinutiNormal":3910,
		"shinutiHard":2270,
		"shinutiMania":1690,
		"shinutiUra":0,
		"shinutiEasyDuet":6310,
		"shinutiNormalDuet":3910,
		"shinutiHardDuet":2270,
		"shinutiManiaDuet":1690,
		"shinutiUraDuet":0,
		"scoreEasy":1000180,
		"scoreNormal":1000450,
		"scoreHard":1003600,
		"scoreMania":1002110,
		"scoreUra":0,
		"previewPos":13402,
		"fumenOffsetPos":20,
		"songName": {
			"text": "RAINMAKER",
			"font": 0,
			"jpText": "RAINMAKER",
			"jpFont": 0,
			"enText": "RAINMAKER",
			"enFont": 1,
			"krText": "RAINMAKER",
			"krFont": 4
		},
		"songSubtitle": {
			"text": "新日本プロレス オカダ・カズチカ入場テーマ",
			"font": 0,
			"jpText": "新日本プロレス オカダ・カズチカ入場テーマ",
			"jpFont": 0,
			"enText": "New Japan Pro Wrestling Kazuchika Okada Entrance Theme",
			"enFont": 1,
			"krText": "신일본 프로레슬링 오카다 카즈치카 입장 테마",
			"krFont": 4
		},
		"songDetail": {
			"text": "",
			"font": 0,
			"jpText": "",
			"jpFont": 0,
			"enText": "",
			"enFont": 0,
			"krText": "",
			"krFont": 0
		}
	}