	{
		"uniqueId":1073,
		"id":"krkrkk",
		"songFileName":"song_krkrkk",
		"order":1846,
		"genreNo":1,
		"branchEasy":false,
		"branchNormal":false,
		"branchHard":false,
		"branchMania":false,
		"branchUra":false,
		"starEasy":3,
		"starNormal":3,
		"starHard":5,
		"starMania":8,
		"starUra":0,
		"shinutiEasy":12350,
		"shinutiNormal":7470,
		"shinutiHard":3710,
		"shinutiMania":2050,
		"shinutiUra":0,
		"shinutiEasyDuet":12350,
		"shinutiNormalDuet":7470,
		"shinutiHardDuet":3710,
		"shinutiManiaDuet":2050,
		"shinutiUraDuet":0,
		"scoreEasy":1000350,
		"scoreNormal":1000980,
		"scoreHard":1001700,
		"scoreMania":1000400,
		"scoreUra":0,
		"previewPos":40601,
		"fumenOffsetPos":0,
		"songName": {
			"text": "ころころここたま！",
			"font": 0,
			"jpText": "ころころここたま！",
			"jpFont": 0,
			"enText": "Korokoro Cocotama!",
			"enFont": 1,
			"krText": "코로코로 코코타마!",
			"krFont": 4
		},
		"songSubtitle": {
			"text": "「かみさまみならい ヒミツのここたま」より",
			"font": 0,
			"jpText": "「かみさまみならい ヒミツのここたま」より",
			"jpFont": 0,
			"enText": "From \" Kamisama Minarai:Himitsu no Cocotama \"",
			"enFont": 1,
			"krText": "\"견습실 비밀의 코코타마\"에서",
			"krFont": 4
		},
		"songDetail": {
			"text": "",
			"font": 0,
			"jpText": "",
			"jpFont": 0,
			"enText": "ころころここたま！",
			"enFont": 0,
			"krText": "ころころここたま！",
			"krFont": 0
		}
	}