	{
		"uniqueId":604,
		"id":"rrsam",
		"songFileName":"song_rrsam",
		"order":2346,
		"genreNo":6,
		"branchEasy":false,
		"branchNormal":false,
		"branchHard":false,
		"branchMania":false,
		"branchUra":false,
		"starEasy":4,
		"starNormal":5,
		"starHard":7,
		"starMania":8,
		"starUra":9,
		"shinutiEasy":4680,
		"shinutiNormal":2810,
		"shinutiHard":1520,
		"shinutiMania":1100,
		"shinutiUra":1100,
		"shinutiEasyDuet":4680,
		"shinutiNormalDuet":2810,
		"shinutiHardDuet":1520,
		"shinutiManiaDuet":1100,
		"shinutiUraDuet":1100,
		"scoreEasy":1001760,
		"scoreNormal":1000340,
		"scoreHard":1000680,
		"scoreMania":1006150,
		"scoreUra":1120,
		"previewPos":63607,
		"fumenOffsetPos":20,
		"songName": {
			"text": "SAMURAI ROCKET",
			"font": 0,
			"jpText": "SAMURAI ROCKET",
			"jpFont": 0,
			"enText": "SAMURAI ROCKET",
			"enFont": 1,
			"krText": "SAMURAI ROCKET",
			"krFont": 4
		},
		"songSubtitle": {
			"text": "「RIDGE RACER V」より",
			"font": 0,
			"jpText": "「RIDGE RACER V」より",
			"jpFont": 0,
			"enText": "From \" RIDGE RACER V \"",
			"enFont": 1,
			"krText": "\"RIDGER RACER V\"에서",
			"krFont": 4
		},
		"songDetail": {
			"text": "",
			"font": 0,
			"jpText": "",
			"jpFont": 0,
			"enText": "",
			"enFont": 0,
			"krText": "",
			"krFont": 0
		}
	}