	{
		"uniqueId":559,
		"id":"pridon",
		"songFileName":"song_pridon",
		"order":2235,
		"genreNo":7,
		"branchEasy":false,
		"branchNormal":false,
		"branchHard":false,
		"branchMania":false,
		"branchUra":false,
		"starEasy":4,
		"starNormal":5,
		"starHard":5,
		"starMania":9,
		"starUra":0,
		"shinutiEasy":5050,
		"shinutiNormal":3510,
		"shinutiHard":2280,
		"shinutiMania":1310,
		"shinutiUra":0,
		"shinutiEasyDuet":5050,
		"shinutiNormalDuet":3510,
		"shinutiHardDuet":2280,
		"shinutiManiaDuet":1310,
		"shinutiUraDuet":0,
		"scoreEasy":1001950,
		"scoreNormal":1001740,
		"scoreHard":1000480,
		"scoreMania":1006750,
		"scoreUra":0,
		"previewPos":13600,
		"fumenOffsetPos":20,
		"songName": {
			"text": "Princess of Donder",
			"font": 0,
			"jpText": "Princess of Donder",
			"jpFont": 0,
			"enText": "Princess of Donder",
			"enFont": 1,
			"krText": "Princess of Donder",
			"krFont": 4
		},
		"songSubtitle": {
			"text": "MOES feat.海保えりか",
			"font": 0,
			"jpText": "MOES feat.海保えりか",
			"jpFont": 0,
			"enText": "MOES feat.Erika Kaiho",
			"enFont": 1,
			"krText": "MOES feat.카이호 에리카",
			"krFont": 4
		},
		"songDetail": {
			"text": "",
			"font": 0,
			"jpText": "",
			"jpFont": 0,
			"enText": "",
			"enFont": 0,
			"krText": "",
			"krFont": 0
		}
	}