	{
		"uniqueId":151,
		"id":"crosbl",
		"songFileName":"song_crosbl",
		"order":1258,
		"genreNo":7,
		"branchEasy":false,
		"branchNormal":false,
		"branchHard":false,
		"branchMania":false,
		"branchUra":false,
		"starEasy":4,
		"starNormal":6,
		"starHard":7,
		"starMania":9,
		"starUra":0,
		"shinutiEasy":5510,
		"shinutiNormal":2980,
		"shinutiHard":1570,
		"shinutiMania":1040,
		"shinutiUra":0,
		"shinutiEasyDuet":5510,
		"shinutiNormalDuet":2980,
		"shinutiHardDuet":1570,
		"shinutiManiaDuet":1040,
		"shinutiUraDuet":0,
		"scoreEasy":1001300,
		"scoreNormal":1000140,
		"scoreHard":1002880,
		"scoreMania":1000480,
		"scoreUra":0,
		"previewPos":51439,
		"fumenOffsetPos":20,
		"songName": {
			"text": "クロス・ブルー",
			"font": 0,
			"jpText": "クロス・ブルー",
			"jpFont": 0,
			"enText": "Cross Blue",
			"enFont": 1,
			"krText": "크로스·블루",
			"krFont": 4
		},
		"songSubtitle": {
			"text": "",
			"font": 0,
			"jpText": "",
			"jpFont": 0,
			"enText": "",
			"enFont": 1,
			"krText": "",
			"krFont": 4
		},
		"songDetail": {
			"text": "",
			"font": 0,
			"jpText": "",
			"jpFont": 0,
			"enText": "クロス・ブルー",
			"enFont": 0,
			"krText": "クロス・ブルー",
			"krFont": 0
		}
	}