	{
		"uniqueId":1462,
		"id":"shtage",
		"songFileName":"song_shtage",
		"order":1537,
		"genreNo":1,
		"branchEasy":false,
		"branchNormal":false,
		"branchHard":false,
		"branchMania":false,
		"branchUra":false,
		"starEasy":2,
		"starNormal":2,
		"starHard":3,
		"starMania":6,
		"starUra":0,
		"shinutiEasy":8830,
		"shinutiNormal":7300,
		"shinutiHard":3920,
		"shinutiMania":2440,
		"shinutiUra":0,
		"shinutiEasyDuet":8830,
		"shinutiNormalDuet":7300,
		"shinutiHardDuet":3920,
		"shinutiManiaDuet":2440,
		"shinutiUraDuet":0,
		"scoreEasy":1000320,
		"scoreNormal":1000000,
		"scoreHard":1001280,
		"scoreMania":1002740,
		"scoreUra":0,
		"previewPos":61769,
		"fumenOffsetPos":0,
		"songName": {
			"text": "Hacking to the Gate",
			"font": 0,
			"jpText": "Hacking to the Gate",
			"jpFont": 0,
			"enText": "Hacking to the Gate",
			"enFont": 1,
			"krText": "",
			"krFont": 4
		},
		"songSubtitle": {
			"text": "TVアニメ「シュタインズ・ゲート」より",
			"font": 0,
			"jpText": "TVアニメ「シュタインズ・ゲート」より",
			"jpFont": 0,
			"enText": "From \" Steins;Gate \"",
			"enFont": 1,
			"krText": "",
			"krFont": 4
		},
		"songDetail": {
			"text": "",
			"font": 0,
			"jpText": "",
			"jpFont": 0,
			"enText": "",
			"enFont": 0,
			"krText": "",
			"krFont": 0
		}
	}