	{
		"uniqueId":1502,
		"id":"shugei",
		"songFileName":"song_shugei",
		"order":1823,
		"genreNo":7,
		"branchEasy":false,
		"branchNormal":false,
		"branchHard":false,
		"branchMania":false,
		"branchUra":false,
		"starEasy":4,
		"starNormal":4,
		"starHard":6,
		"starMania":7,
		"starUra":0,
		"shinutiEasy":7580,
		"shinutiNormal":5560,
		"shinutiHard":2780,
		"shinutiMania":2120,
		"shinutiUra":0,
		"shinutiEasyDuet":7580,
		"shinutiNormalDuet":5560,
		"shinutiHardDuet":2780,
		"shinutiManiaDuet":2120,
		"shinutiUraDuet":0,
		"scoreEasy":1000560,
		"scoreNormal":1000800,
		"scoreHard":1003580,
		"scoreMania":1002760,
		"scoreUra":0,
		"previewPos":3564,
		"fumenOffsetPos":0,
		"songName": {
			"text": "ニッティング・ハイ",
			"font": 0,
			"jpText": "ニッティング・ハイ",
			"jpFont": 0,
			"enText": "Knitting High",
			"enFont": 1,
			"krText": "",
			"krFont": 4
		},
		"songSubtitle": {
			"text": "",
			"font": 0,
			"jpText": "",
			"jpFont": 0,
			"enText": "",
			"enFont": 1,
			"krText": "",
			"krFont": 4
		},
		"songDetail": {
			"text": "",
			"font": 0,
			"jpText": "",
			"jpFont": 0,
			"enText": "ニッティング・ハイ",
			"enFont": 0,
			"krText": "",
			"krFont": 0
		}
	}